README
setup.py
downlink/__init__.py
downlink/__main__.py
downlink/document_linkscraper.py
downlink/linkscraper.py
downlink.egg-info/PKG-INFO
downlink.egg-info/SOURCES.txt
downlink.egg-info/dependency_links.txt
downlink.egg-info/entry_points.txt
downlink.egg-info/requires.txt
downlink.egg-info/top_level.txt
tests/__init__.py
tests/demo.py