Metadata-Version: 1.1
Name: downlink
Version: 0.0.7
Summary: Download all the documents linked from a web page.
Home-page: https://github.com/jakekara/downlink-py
Author: Jake Kara
Author-email: jake@jakekara.com
License: GPL-3
Keywords: example documentation tutorial
Platform: UNKNOWN
Classifier: Development Status :: 2 - Pre-Alpha
Classifier: Topic :: Utilities
Classifier: License :: OSI Approved :: GNU General Public License v3 (GPLv3)
